{
  "$schema": "./SCHEMA.json",
  "job": {
    "id": null,
    "idx": "1",
    "name": "Notify Valuation Officer",
    "label": "Register Property Link",
    "description": "Job for creating and updating information about the relationship between the current persona_ratepayer of a hereditament and the hereditaments list entry they are the current ratepayer of.",
    "origination": "20251019T231624Z",
    "termination": null,
    "category": {
      "code": "LTX-DOM-JOB",
      "meaning": "Local taxation domain job"
    },
    "type": {
      "code": "INF",
      "meaning": "Assisting information"
    },
    "class": {
      "code": "LPP",
      "meaning": "Link ratepayer and property"
    },
    "data": {
      "foreign_ids": [],
      "foreign_names": [],
      "foreign_labels": []
    },
    "protodata": [],
    "metadata": {
      "sending": {
        "extracting": {
          "selecting": {}
        },
        "transforming": {
          "filtering": {},
          "supplementing": {},
          "recontextualising": {}
        },
        "loading": {
          "readying": {},
          "assuring": {},
          "signing": {
            "inputs": {
              "hash": "8aVYF4QqDVP7BQ2VaHoaDbBw85RyCzo4Kl09NQ1Yq2IcicT7TWElDdhsfl/cNX7UoLGFUH3eiM0TPt7hvdi1VQ==",
              "signature": null
            }
          },
          "encrypting": {},
          "sending": {}
        }
      },
      "receiving": {
        "unloading": {
          "receiving": {},
          "decrypting": {},
          "verifying": {},
          "assuring": {},
          "readying": {}
        },
        "transforming": {
          "recontextualising": {},
          "dropping": {},
          "restoring": {}
        },
        "storing": {
          "inserting": {}
        }
      }
    },
    "compartments": {
      "properties": [
        {
          "id": 2,
          "idx": null,
          "name": null,
          "label": null,
          "description": null,
          "origination": "20000101T000000Z",
          "termination": null,
          "category": {
            "code": "LTX-DOM-PRP",
            "meaning": "Local taxation domain property (LGFA88+92)"
          },
          "type": {
            "code": "OCC",
            "meaning": "Constituted by reference to actual occupation (LGFA88+92=>GRA67=>CommonLaw)"
          },
          "class": {
            "code": "HDT",
            "meaning": "Statutory NDR hereditament (LGFA88s64(1))"
          },
          "data": {
            "foreign_ids": [
              {
                "system": "CDB",
                "location": "hmrc/voa/cdb/add_view",
                "value": "55821184"
              },
              {
                "system": "NLPG",
                "location": "https://services.geoplace.co.uk/",
                "value": "100041063576"
              }
            ],
            "foreign_names": [],
            "foreign_labels": [],
            "addresses": {
              "property_full_address": "16, NEW GEORGE STREET, PLYMOUTH, PL1 1RL",
              "address_line_1": "16",
              "address_postcode": "PL1 1RL",
              "address_known_as": null
            },
            "location": {
              "local_authority_pseudo_area_code": "1160",
              "ordanace_survey_coordinates": null,
              "google_maps_coordinates": null
            },
            "assessments": [
              {
                "id": 2,
                "idx": null,
                "name": null,
                "label": null,
                "description": null,
                "origination": "20230825T124233Z",
                "termination": null,
                "category": {
                  "code": "LTX-DOM-AST",
                  "meaning": "Local taxation domain assessment (LGFA88+92)"
                },
                "type": {
                  "code": "CHG",
                  "meaning": "To be determined (To be determined)"
                },
                "class": {
                  "code": "RLE",
                  "meaning": "To be determined (To be determined)"
                },
                "data": {
                  "foreign_ids": [
                    {
                      "system": "CDB",
                      "location": "hmrc/voa/cdb/ndr_assessments",
                      "value": "27399677000"
                    }
                  ],
                  "foreign_names": [],
                  "foreign_labels": [],
                  "property": {
                    "id": 2,
                    "cdb_id": 55821184
                  },
                  "use": {
                    "is_composite": "N",
                    "is_part_exempt": "N",
                    "description": "RESTAURANT AND PREMISES RESTAURANT AND PREMISES"
                  },
                  "valuation_surveys": [],
                  "valuations": [],
                  "valuation": {
                    "method_code": "234",
                    "rateable_value": 76500,
                    "effective_date": "20230529T000000Z"
                  },
                  "list": {
                    "category": "LTX-DOM-LST",
                    "function": "Charging",
                    "year": "2023",
                    "authority_code": "1160"
                  },
                  "workflow": {
                    "cdb_job_id": 39115380283
                  }
                },
                "protodata": [],
                "metadata": {
                  "sending": {
                    "extracting": {
                      "selecting": {}
                    },
                    "transforming": {
                      "filtering": {},
                      "supplementing": {},
                      "recontextualising": {}
                    },
                    "loading": {
                      "readying": {},
                      "assuring": {},
                      "signing": {},
                      "encrypting": {},
                      "sending": {}
                    }
                  },
                  "receiving": {
                    "unloading": {
                      "receiving": {},
                      "decrypting": {},
                      "verifying": {},
                      "assuring": {},
                      "readying": {}
                    },
                    "transforming": {
                      "recontextualising": {},
                      "dropping": {},
                      "restoring": {}
                    },
                    "storing": {
                      "inserting": {}
                    }
                  }
                },
                "compartments": {},
                "items": []
              }
            ]
          },
          "protodata": [],
          "metadata": {
            "sending": {
              "extracting": {
                "selecting": {}
              },
              "transforming": {
                "filtering": {},
                "supplementing": {},
                "recontextualising": {}
              },
              "loading": {
                "readying": {},
                "assuring": {},
                "signing": {},
                "encrypting": {},
                "sending": {}
              }
            },
            "receiving": {
              "unloading": {
                "receiving": {},
                "decrypting": {},
                "verifying": {},
                "assuring": {},
                "readying": {}
              },
              "transforming": {
                "recontextualising": {},
                "dropping": {},
                "restoring": {}
              },
              "storing": {
                "inserting": {}
              }
            }
          },
          "compartments": {},
          "items": []
        }
      ],
      "persons": [
        {
          "id": 1,
          "idx": "1.4.1",
          "name": "Government Gateway User",
          "label": "Authenticated Government Gateway System User",
          "description": "A Government Gateway authenticated natural, corporate or crown user of online services provided by the UK Government/HMRC whose type and class are now known or re-confirmed.",
          "origination": null,
          "termination": null,
          "category": {
            "code": "LTX-DOM-PSN",
            "meaning": "Local taxation domain person"
          },
          "type": {
            "code": "COR",
            "meaning": "Corporate"
          },
          "class": {
            "code": "GGY",
            "meaning": "Any government gateway user"
          },
          "data": {
            "foreign_ids": [
              {
                "system": "Government_Gateway",
                "location": null,
                "value": "GG123456789"
              },
              {
                "system": "Companies_House",
                "location": "https://find-and-update.company-information.service.gov.uk/company/",
                "value": "07101365"
              }
            ],
            "foreign_names": [],
            "foreign_labels": [],
            "names": {
              "title_common": null,
              "title_uncommon": null,
              "forenames": null,
              "surname": null,
              "post_nominals": null,
              "corporate_name": "CHOPSTIX RESTAURANT LIMITED",
              "crown_name": null,
              "known_as": "Subsiduary of CHOPSTIX GROUP LTD (10702275)"
            },
            "communications": {
              "postal_address": "29a Kentish Town Road, London, England, NW1 8NL",
              "telephone_number": null,
              "email": null
            }
          },
          "protodata": [],
          "metadata": {
            "sending": {
              "extracting": {
                "selecting": {}
              },
              "transforming": {
                "filtering": {},
                "supplementing": {},
                "recontextualising": {}
              },
              "loading": {
                "readying": {},
                "assuring": {},
                "signing": {},
                "encrypting": {},
                "sending": {}
              }
            },
            "receiving": {
              "unloading": {
                "receiving": {},
                "decrypting": {},
                "verifying": {},
                "assuring": {},
                "readying": {}
              },
              "transforming": {
                "recontextualising": {},
                "dropping": {},
                "restoring": {}
              },
              "storing": {
                "inserting": {}
              }
            }
          },
          "compartments": {},
          "items": [
            {
              "id": 1,
              "idx": "1.2.1.1",
              "name": "Local Taxation Persona",
              "label": "Authenticated Local Taxation Persona",
              "description": "A local taxation domain authenticated persona whose type and class are not yet known or re-confirmed, and that is assignable to the person.",
              "origination": null,
              "termination": null,
              "category": {
                "code": "LTX-DOM-PSA",
                "meaning": "Local taxation domain persona"
              },
              "type": {
                "code": "TXP",
                "meaning": "LGFA taxpayer"
              },
              "class": {
                "code": "RPO",
                "meaning": "Ratepayer (occupier) (LGFA88s43(1))"
              },
              "data": {
                "foreign_ids": [],
                "foreign_names": [],
                "foreign_labels": [],
                "names": {
                  "title_common": null,
                  "title_uncommon": null,
                  "forenames": null,
                  "surname": null,
                  "post_nominals": null,
                  "corporate_name": "CHOPSTIX RESTAURANT LIMITED",
                  "crown_name": null,
                  "known_as": "CHOPSTIX Plymouth"
                },
                "communications": {
                  "postal_address": "16 New George St, Plymouth PL1 1RL",
                  "telephone_number": null,
                  "email": null
                }
              },
              "protodata": [],
              "metadata": {
                "sending": {
                  "extracting": {
                    "selecting": {}
                  },
                  "transforming": {
                    "filtering": {},
                    "supplementing": {},
                    "recontextualising": {}
                  },
                  "loading": {
                    "readying": {},
                    "assuring": {},
                    "signing": {},
                    "encrypting": {},
                    "sending": {}
                  }
                },
                "receiving": {
                  "unloading": {
                    "receiving": {},
                    "decrypting": {},
                    "verifying": {},
                    "assuring": {},
                    "readying": {}
                  },
                  "transforming": {
                    "recontextualising": {},
                    "dropping": {},
                    "restoring": {}
                  },
                  "storing": {
                    "inserting": {}
                  }
                }
              },
              "compartments": {},
              "items": []
            }
          ]
        }
      ],
      "processes": [
        {
          "id": null,
          "idx": "1.3.1",
          "name": "Persona-Property Linking",
          "label": "Ratepayer-ListEntry and Ratepayer-Agent Linking",
          "description": "A local taxtion domain process producing persisted records about relationships between LGFA88shd9para4J person-personas and LGFA88 hereditaments for which such personas are obliged to provide LGFA88shd9para4I(1) notofiable information.",
          "origination": null,
          "termination": null,
          "category": {
            "code": "LTX-DOM-PRS",
            "meaning": "Local taxation domain process (Local Government Finance Acts + IA78s12(1))"
          },
          "type": {
            "code": "LRL",
            "meaning": "Local rating list process (LGFA88ptIII Valuation Officer functions)"
          },
          "class": {
            "code": "SLL",
            "meaning": "Supply of assisting information to Local Valuation Officers (LGFA88s41(4)|41ZA(5) Local rating list accuracy)"
          },
          "data": {
            "foreign_ids": [],
            "foreign_names": [],
            "foreign_labels": [],
            "documentation": {
              "webpage": null
            }
          },
          "protodata": [],
          "metadata": {
            "sending": {
              "extracting": {
                "selecting": {}
              },
              "transforming": {
                "filtering": {},
                "supplementing": {},
                "recontextualising": {}
              },
              "loading": {
                "readying": {},
                "assuring": {},
                "signing": {},
                "encrypting": {},
                "sending": {}
              }
            },
            "receiving": {
              "unloading": {
                "receiving": {},
                "decrypting": {},
                "verifying": {},
                "assuring": {},
                "readying": {}
              },
              "transforming": {
                "recontextualising": {},
                "dropping": {},
                "restoring": {}
              },
              "storing": {
                "inserting": {}
              }
            }
          },
          "compartments": {},
          "items": []
        }
      ],
      "products": [
        {
          "id": null,
          "idx": "1.4.1",
          "name": "Property Link",
          "label": "Ratepayer-ListEntry-Property Link",
          "description": "A relationships between LGFA88shd9para4J person-personas and LGFA88 hereditaments for which such personas are obliged to provide LGFA88shd9para4I(1) notofiable information.",
          "origination": null,
          "termination": null,
          "category": {
            "code": "LTX-DOM-REL",
            "meaning": "Local taxation domain relationship"
          },
          "type": {
            "code": "LIB",
            "meaning": "Liability | One entity is liable for other entity(s) and the other entity(s) are the basis for the liabilities extent"
          },
          "class": {
            "code": "",
            "meaning": ""
          },
          "data": {
            "foreign_ids": [],
            "foreign_names": [],
            "foreign_labels": [],
            "manifestations": [
              {
                "artifact_reference": null,
                "artifact_code": null,
                "artifact_description": null,
                "issued_date": null,
                "withdrawn_date": null,
                "effective_from_date": null,
                "effective_to_date": null,
                "observed_date": null,
                "operative_area_code": null,
                "operative_area_name": null,
                "protodata_ptr": null,
                "notes": null
              }
            ]
          },
          "protodata": [],
          "metadata": {
            "sending": {
              "extracting": {
                "selecting": {}
              },
              "transforming": {
                "filtering": {},
                "supplementing": {},
                "recontextualising": {}
              },
              "loading": {
                "readying": {},
                "assuring": {},
                "signing": {},
                "encrypting": {},
                "sending": {}
              }
            },
            "receiving": {
              "unloading": {
                "receiving": {},
                "decrypting": {},
                "verifying": {},
                "assuring": {},
                "readying": {}
              },
              "transforming": {
                "recontextualising": {},
                "dropping": {},
                "restoring": {}
              },
              "storing": {
                "inserting": {}
              }
            }
          },
          "compartments": {},
          "items": [
            {
              "transportation": {
                "path": "/job/compartments/persons/@id=#/items/@id=#"
              },
              "persistence": {
                "place": "LTX-DOM-PSA",
                "identifier": null
              }
            },
            {
              "transportation": {
                "path": "/job/compartments/properties/@id=#/data/assessments/@id=#"
              },
              "persistence": {
                "place": "LTX-DOM-AST",
                "identifier": null
              }
            }
          ]
        }
      ],
      "relationships": [
        {
          "id": null,
          "idx": "1.5.1",
          "name": "Property Link",
          "label": "Ratepayer-ListEntry-Property Link",
          "description": "A relationships between LGFA88shd9para4J person-personas and LGFA88 hereditaments for which such personas are obliged to provide LGFA88shd9para4I(1) notofiable information.",
          "origination": null,
          "termination": null,
          "category": {
            "code": "LTX-DOM-REL",
            "meaning": "Local taxation domain relationship"
          },
          "type": {
            "code": "LIB",
            "meaning": "Liability | One entity is liable for other entity(s) and the other entity(s) are the basis for the liabilities extent"
          },
          "class": {
            "code": "",
            "meaning": ""
          },
          "data": {
            "foreign_ids": [],
            "foreign_names": [],
            "foreign_labels": [],
            "manifestations": [
              {
                "artifact_reference": null,
                "artifact_code": null,
                "artifact_description": null,
                "issued_date": null,
                "withdrawn_date": null,
                "effective_from_date": null,
                "effective_to_date": null,
                "observed_date": null,
                "operative_area_code": null,
                "operative_area_name": null,
                "protodata_ptr": null,
                "notes": null
              }
            ]
          },
          "protodata": [],
          "metadata": {
            "sending": {
              "extracting": {
                "selecting": {}
              },
              "transforming": {
                "filtering": {},
                "supplementing": {},
                "recontextualising": {}
              },
              "loading": {
                "readying": {},
                "assuring": {},
                "signing": {},
                "encrypting": {},
                "sending": {}
              }
            },
            "receiving": {
              "unloading": {
                "receiving": {},
                "decrypting": {},
                "verifying": {},
                "assuring": {},
                "readying": {}
              },
              "transforming": {
                "recontextualising": {},
                "dropping": {},
                "restoring": {}
              },
              "storing": {
                "inserting": {}
              }
            }
          },
          "compartments": {},
          "items": [
            {
              "transportation": {
                "path": "/job/compartments/persons/@id=#/items/@id=#"
              },
              "persistence": {
                "place": "LTX-DOM-PSA",
                "identifier": null
              }
            },
            {
              "transportation": {
                "path": "/job/compartments/properties/@id=#/data/assessments/@id=#"
              },
              "persistence": {
                "place": "LTX-DOM-AST",
                "identifier": null
              }
            }
          ]
        }
      ]
    },
    "items": []
  }
}